<annotation>
	<folder></folder>
	<filename>1478732743611832082_jpg.rf.491b64257dd1791a27da497a076d9fd8.jpg</filename>
	<path>1478732743611832082_jpg.rf.491b64257dd1791a27da497a076d9fd8.jpg</path>
	<source>
		<database>roboflow.ai</database>
	</source>
	<size>
		<width>512</width>
		<height>512</height>
		<depth>3</depth>
	</size>
	<segmented>0</segmented>
	<object>
		<name>car</name>
		<pose>Unspecified</pose>
		<truncated>0</truncated>
		<difficult>0</difficult>
		<occluded>0</occluded>
		<bndbox>
			<xmin>60</xmin>
			<xmax>72</xmax>
			<ymin>252</ymin>
			<ymax>278</ymax>
		</bndbox>
	</object>
	<object>
		<name>car</name>
		<pose>Unspecified</pose>
		<truncated>0</truncated>
		<difficult>0</difficult>
		<occluded>0</occluded>
		<bndbox>
			<xmin>65</xmin>
			<xmax>99</xmax>
			<ymin>246</ymin>
			<ymax>273</ymax>
		</bndbox>
	</object>
	<object>
		<name>car</name>
		<pose>Unspecified</pose>
		<truncated>0</truncated>
		<difficult>0</difficult>
		<occluded>0</occluded>
		<bndbox>
			<xmin>67</xmin>
			<xmax>104</xmax>
			<ymin>242</ymin>
			<ymax>278</ymax>
		</bndbox>
	</object>
	<object>
		<name>car</name>
		<pose>Unspecified</pose>
		<truncated>0</truncated>
		<difficult>0</difficult>
		<occluded>0</occluded>
		<bndbox>
			<xmin>111</xmin>
			<xmax>135</xmax>
			<ymin>245</ymin>
			<ymax>276</ymax>
		</bndbox>
	</object>
	<object>
		<name>car</name>
		<pose>Unspecified</pose>
		<truncated>0</truncated>
		<difficult>0</difficult>
		<occluded>0</occluded>
		<bndbox>
			<xmin>112</xmin>
			<xmax>136</xmax>
			<ymin>246</ymin>
			<ymax>271</ymax>
		</bndbox>
	</object>
	<object>
		<name>car</name>
		<pose>Unspecified</pose>
		<truncated>0</truncated>
		<difficult>0</difficult>
		<occluded>0</occluded>
		<bndbox>
			<xmin>133</xmin>
			<xmax>148</xmax>
			<ymin>251</ymin>
			<ymax>267</ymax>
		</bndbox>
	</object>
	<object>
		<name>car</name>
		<pose>Unspecified</pose>
		<truncated>0</truncated>
		<difficult>0</difficult>
		<occluded>0</occluded>
		<bndbox>
			<xmin>169</xmin>
			<xmax>188</xmax>
			<ymin>242</ymin>
			<ymax>271</ymax>
		</bndbox>
	</object>
	<object>
		<name>trafficLight-Red</name>
		<pose>Unspecified</pose>
		<truncated>0</truncated>
		<difficult>0</difficult>
		<occluded>0</occluded>
		<bndbox>
			<xmin>172</xmin>
			<xmax>180</xmax>
			<ymin>234</ymin>
			<ymax>247</ymax>
		</bndbox>
	</object>
	<object>
		<name>trafficLight-Red</name>
		<pose>Unspecified</pose>
		<truncated>0</truncated>
		<difficult>0</difficult>
		<occluded>0</occluded>
		<bndbox>
			<xmin>208</xmin>
			<xmax>215</xmax>
			<ymin>222</ymin>
			<ymax>238</ymax>
		</bndbox>
	</object>
	<object>
		<name>trafficLight-Green</name>
		<pose>Unspecified</pose>
		<truncated>0</truncated>
		<difficult>0</difficult>
		<occluded>0</occluded>
		<bndbox>
			<xmin>233</xmin>
			<xmax>241</xmax>
			<ymin>198</ymin>
			<ymax>215</ymax>
		</bndbox>
	</object>
	<object>
		<name>car</name>
		<pose>Unspecified</pose>
		<truncated>0</truncated>
		<difficult>0</difficult>
		<occluded>0</occluded>
		<bndbox>
			<xmin>262</xmin>
			<xmax>280</xmax>
			<ymin>245</ymin>
			<ymax>267</ymax>
		</bndbox>
	</object>
	<object>
		<name>car</name>
		<pose>Unspecified</pose>
		<truncated>0</truncated>
		<difficult>0</difficult>
		<occluded>0</occluded>
		<bndbox>
			<xmin>263</xmin>
			<xmax>280</xmax>
			<ymin>249</ymin>
			<ymax>271</ymax>
		</bndbox>
	</object>
	<object>
		<name>trafficLight-Green</name>
		<pose>Unspecified</pose>
		<truncated>0</truncated>
		<difficult>0</difficult>
		<occluded>0</occluded>
		<bndbox>
			<xmin>281</xmin>
			<xmax>286</xmax>
			<ymin>222</ymin>
			<ymax>241</ymax>
		</bndbox>
	</object>
	<object>
		<name>trafficLight-Green</name>
		<pose>Unspecified</pose>
		<truncated>0</truncated>
		<difficult>0</difficult>
		<occluded>0</occluded>
		<bndbox>
			<xmin>285</xmin>
			<xmax>290</xmax>
			<ymin>225</ymin>
			<ymax>239</ymax>
		</bndbox>
	</object>
	<object>
		<name>car</name>
		<pose>Unspecified</pose>
		<truncated>0</truncated>
		<difficult>0</difficult>
		<occluded>0</occluded>
		<bndbox>
			<xmin>295</xmin>
			<xmax>330</xmax>
			<ymin>243</ymin>
			<ymax>290</ymax>
		</bndbox>
	</object>
	<object>
		<name>truck</name>
		<pose>Unspecified</pose>
		<truncated>0</truncated>
		<difficult>0</difficult>
		<occluded>0</occluded>
		<bndbox>
			<xmin>310</xmin>
			<xmax>339</xmax>
			<ymin>225</ymin>
			<ymax>257</ymax>
		</bndbox>
	</object>
</annotation>
