<annotation>
	<folder></folder>
	<filename>1478021668074935419_jpg.rf.be54e90cf66ae94c60a299de5250839d.jpg</filename>
	<path>1478021668074935419_jpg.rf.be54e90cf66ae94c60a299de5250839d.jpg</path>
	<source>
		<database>roboflow.ai</database>
	</source>
	<size>
		<width>512</width>
		<height>512</height>
		<depth>3</depth>
	</size>
	<segmented>0</segmented>
	<object>
		<name>car</name>
		<pose>Unspecified</pose>
		<truncated>0</truncated>
		<difficult>0</difficult>
		<occluded>0</occluded>
		<bndbox>
			<xmin>1</xmin>
			<xmax>339</xmax>
			<ymin>173</ymin>
			<ymax>431</ymax>
		</bndbox>
	</object>
</annotation>
