<annotation>
	<folder></folder>
	<filename>1478899064417898822_jpg.rf.bb1cf459a6682ac7ad8712b09583faea.jpg</filename>
	<path>1478899064417898822_jpg.rf.bb1cf459a6682ac7ad8712b09583faea.jpg</path>
	<source>
		<database>roboflow.ai</database>
	</source>
	<size>
		<width>512</width>
		<height>512</height>
		<depth>3</depth>
	</size>
	<segmented>0</segmented>
	<object>
		<name>car</name>
		<pose>Unspecified</pose>
		<truncated>0</truncated>
		<difficult>0</difficult>
		<occluded>0</occluded>
		<bndbox>
			<xmin>255</xmin>
			<xmax>276</xmax>
			<ymin>277</ymin>
			<ymax>302</ymax>
		</bndbox>
	</object>
	<object>
		<name>car</name>
		<pose>Unspecified</pose>
		<truncated>0</truncated>
		<difficult>0</difficult>
		<occluded>0</occluded>
		<bndbox>
			<xmin>259</xmin>
			<xmax>274</xmax>
			<ymin>277</ymin>
			<ymax>305</ymax>
		</bndbox>
	</object>
	<object>
		<name>car</name>
		<pose>Unspecified</pose>
		<truncated>0</truncated>
		<difficult>0</difficult>
		<occluded>0</occluded>
		<bndbox>
			<xmin>273</xmin>
			<xmax>310</xmax>
			<ymin>268</ymin>
			<ymax>308</ymax>
		</bndbox>
	</object>
	<object>
		<name>car</name>
		<pose>Unspecified</pose>
		<truncated>0</truncated>
		<difficult>0</difficult>
		<occluded>0</occluded>
		<bndbox>
			<xmin>274</xmin>
			<xmax>308</xmax>
			<ymin>269</ymin>
			<ymax>310</ymax>
		</bndbox>
	</object>
	<object>
		<name>car</name>
		<pose>Unspecified</pose>
		<truncated>0</truncated>
		<difficult>0</difficult>
		<occluded>0</occluded>
		<bndbox>
			<xmin>307</xmin>
			<xmax>373</xmax>
			<ymin>245</ymin>
			<ymax>324</ymax>
		</bndbox>
	</object>
</annotation>
