<annotation>
	<folder></folder>
	<filename>1478898556541257115_jpg.rf.3e7d776ece0c3c968714157fbe1f635e.jpg</filename>
	<path>1478898556541257115_jpg.rf.3e7d776ece0c3c968714157fbe1f635e.jpg</path>
	<source>
		<database>roboflow.ai</database>
	</source>
	<size>
		<width>512</width>
		<height>512</height>
		<depth>3</depth>
	</size>
	<segmented>0</segmented>
	<object>
		<name>car</name>
		<pose>Unspecified</pose>
		<truncated>0</truncated>
		<difficult>0</difficult>
		<occluded>0</occluded>
		<bndbox>
			<xmin>1</xmin>
			<xmax>73</xmax>
			<ymin>254</ymin>
			<ymax>342</ymax>
		</bndbox>
	</object>
	<object>
		<name>truck</name>
		<pose>Unspecified</pose>
		<truncated>0</truncated>
		<difficult>0</difficult>
		<occluded>0</occluded>
		<bndbox>
			<xmin>127</xmin>
			<xmax>407</xmax>
			<ymin>173</ymin>
			<ymax>399</ymax>
		</bndbox>
	</object>
	<object>
		<name>car</name>
		<pose>Unspecified</pose>
		<truncated>0</truncated>
		<difficult>0</difficult>
		<occluded>0</occluded>
		<bndbox>
			<xmin>130</xmin>
			<xmax>403</xmax>
			<ymin>178</ymin>
			<ymax>393</ymax>
		</bndbox>
	</object>
</annotation>
