<annotation>
	<folder></folder>
	<filename>1478901452980159343_jpg.rf.69540065bd4ad5564daec5f042013662.jpg</filename>
	<path>1478901452980159343_jpg.rf.69540065bd4ad5564daec5f042013662.jpg</path>
	<source>
		<database>roboflow.ai</database>
	</source>
	<size>
		<width>512</width>
		<height>512</height>
		<depth>3</depth>
	</size>
	<segmented>0</segmented>
	<object>
		<name>car</name>
		<pose>Unspecified</pose>
		<truncated>0</truncated>
		<difficult>0</difficult>
		<occluded>0</occluded>
		<bndbox>
			<xmin>188</xmin>
			<xmax>209</xmax>
			<ymin>263</ymin>
			<ymax>290</ymax>
		</bndbox>
	</object>
	<object>
		<name>car</name>
		<pose>Unspecified</pose>
		<truncated>0</truncated>
		<difficult>0</difficult>
		<occluded>0</occluded>
		<bndbox>
			<xmin>245</xmin>
			<xmax>280</xmax>
			<ymin>242</ymin>
			<ymax>294</ymax>
		</bndbox>
	</object>
	<object>
		<name>car</name>
		<pose>Unspecified</pose>
		<truncated>0</truncated>
		<difficult>0</difficult>
		<occluded>0</occluded>
		<bndbox>
			<xmin>298</xmin>
			<xmax>333</xmax>
			<ymin>245</ymin>
			<ymax>269</ymax>
		</bndbox>
	</object>
</annotation>
