<annotation>
	<folder></folder>
	<filename>1478897232862562678_jpg.rf.XOUcQrqctnwkrh0b7NsD.jpg</filename>
	<path>1478897232862562678_jpg.rf.XOUcQrqctnwkrh0b7NsD.jpg</path>
	<source>
		<database>roboflow.ai</database>
	</source>
	<size>
		<width>512</width>
		<height>512</height>
		<depth>3</depth>
	</size>
	<segmented>0</segmented>
	<object>
		<name>car</name>
		<pose>Unspecified</pose>
		<truncated>0</truncated>
		<difficult>0</difficult>
		<occluded>0</occluded>
		<bndbox>
			<xmin>1</xmin>
			<xmax>34</xmax>
			<ymin>285</ymin>
			<ymax>320</ymax>
		</bndbox>
	</object>
	<object>
		<name>car</name>
		<pose>Unspecified</pose>
		<truncated>0</truncated>
		<difficult>0</difficult>
		<occluded>0</occluded>
		<bndbox>
			<xmin>1</xmin>
			<xmax>41</xmax>
			<ymin>292</ymin>
			<ymax>317</ymax>
		</bndbox>
	</object>
	<object>
		<name>truck</name>
		<pose>Unspecified</pose>
		<truncated>0</truncated>
		<difficult>0</difficult>
		<occluded>0</occluded>
		<bndbox>
			<xmin>73</xmin>
			<xmax>147</xmax>
			<ymin>248</ymin>
			<ymax>326</ymax>
		</bndbox>
	</object>
	<object>
		<name>truck</name>
		<pose>Unspecified</pose>
		<truncated>0</truncated>
		<difficult>0</difficult>
		<occluded>0</occluded>
		<bndbox>
			<xmin>78</xmin>
			<xmax>146</xmax>
			<ymin>248</ymin>
			<ymax>323</ymax>
		</bndbox>
	</object>
	<object>
		<name>car</name>
		<pose>Unspecified</pose>
		<truncated>0</truncated>
		<difficult>0</difficult>
		<occluded>0</occluded>
		<bndbox>
			<xmin>108</xmin>
			<xmax>150</xmax>
			<ymin>283</ymin>
			<ymax>330</ymax>
		</bndbox>
	</object>
	<object>
		<name>car</name>
		<pose>Unspecified</pose>
		<truncated>0</truncated>
		<difficult>0</difficult>
		<occluded>0</occluded>
		<bndbox>
			<xmin>109</xmin>
			<xmax>152</xmax>
			<ymin>277</ymin>
			<ymax>326</ymax>
		</bndbox>
	</object>
	<object>
		<name>trafficLight-Green</name>
		<pose>Unspecified</pose>
		<truncated>0</truncated>
		<difficult>0</difficult>
		<occluded>0</occluded>
		<bndbox>
			<xmin>182</xmin>
			<xmax>195</xmax>
			<ymin>93</ymin>
			<ymax>138</ymax>
		</bndbox>
	</object>
	<object>
		<name>car</name>
		<pose>Unspecified</pose>
		<truncated>0</truncated>
		<difficult>0</difficult>
		<occluded>0</occluded>
		<bndbox>
			<xmin>195</xmin>
			<xmax>209</xmax>
			<ymin>285</ymin>
			<ymax>303</ymax>
		</bndbox>
	</object>
	<object>
		<name>car</name>
		<pose>Unspecified</pose>
		<truncated>0</truncated>
		<difficult>0</difficult>
		<occluded>0</occluded>
		<bndbox>
			<xmin>234</xmin>
			<xmax>248</xmax>
			<ymin>286</ymin>
			<ymax>305</ymax>
		</bndbox>
	</object>
	<object>
		<name>trafficLight-Green</name>
		<pose>Unspecified</pose>
		<truncated>0</truncated>
		<difficult>0</difficult>
		<occluded>0</occluded>
		<bndbox>
			<xmin>302</xmin>
			<xmax>315</xmax>
			<ymin>193</ymin>
			<ymax>234</ymax>
		</bndbox>
	</object>
</annotation>
