<annotation>
	<folder></folder>
	<filename>1478897035767159704_jpg.rf.c3cd06159c508178aaa8c8f15f92427c.jpg</filename>
	<path>1478897035767159704_jpg.rf.c3cd06159c508178aaa8c8f15f92427c.jpg</path>
	<source>
		<database>roboflow.ai</database>
	</source>
	<size>
		<width>512</width>
		<height>512</height>
		<depth>3</depth>
	</size>
	<segmented>0</segmented>
	<object>
		<name>car</name>
		<pose>Unspecified</pose>
		<truncated>0</truncated>
		<difficult>0</difficult>
		<occluded>0</occluded>
		<bndbox>
			<xmin>155</xmin>
			<xmax>176</xmax>
			<ymin>261</ymin>
			<ymax>285</ymax>
		</bndbox>
	</object>
	<object>
		<name>car</name>
		<pose>Unspecified</pose>
		<truncated>0</truncated>
		<difficult>0</difficult>
		<occluded>0</occluded>
		<bndbox>
			<xmin>155</xmin>
			<xmax>177</xmax>
			<ymin>264</ymin>
			<ymax>286</ymax>
		</bndbox>
	</object>
	<object>
		<name>car</name>
		<pose>Unspecified</pose>
		<truncated>0</truncated>
		<difficult>0</difficult>
		<occluded>0</occluded>
		<bndbox>
			<xmin>176</xmin>
			<xmax>195</xmax>
			<ymin>259</ymin>
			<ymax>284</ymax>
		</bndbox>
	</object>
	<object>
		<name>car</name>
		<pose>Unspecified</pose>
		<truncated>0</truncated>
		<difficult>0</difficult>
		<occluded>0</occluded>
		<bndbox>
			<xmin>178</xmin>
			<xmax>197</xmax>
			<ymin>257</ymin>
			<ymax>279</ymax>
		</bndbox>
	</object>
	<object>
		<name>car</name>
		<pose>Unspecified</pose>
		<truncated>0</truncated>
		<difficult>0</difficult>
		<occluded>0</occluded>
		<bndbox>
			<xmin>241</xmin>
			<xmax>260</xmax>
			<ymin>260</ymin>
			<ymax>289</ymax>
		</bndbox>
	</object>
	<object>
		<name>car</name>
		<pose>Unspecified</pose>
		<truncated>0</truncated>
		<difficult>0</difficult>
		<occluded>0</occluded>
		<bndbox>
			<xmin>262</xmin>
			<xmax>318</xmax>
			<ymin>242</ymin>
			<ymax>319</ymax>
		</bndbox>
	</object>
</annotation>
