<annotation>
	<folder></folder>
	<filename>1478898979867133501_jpg.rf.027e84f3b380c8eafc6a2c8d1765a7de.jpg</filename>
	<path>1478898979867133501_jpg.rf.027e84f3b380c8eafc6a2c8d1765a7de.jpg</path>
	<source>
		<database>roboflow.ai</database>
	</source>
	<size>
		<width>512</width>
		<height>512</height>
		<depth>3</depth>
	</size>
	<segmented>0</segmented>
	<object>
		<name>car</name>
		<pose>Unspecified</pose>
		<truncated>0</truncated>
		<difficult>0</difficult>
		<occluded>0</occluded>
		<bndbox>
			<xmin>47</xmin>
			<xmax>110</xmax>
			<ymin>259</ymin>
			<ymax>312</ymax>
		</bndbox>
	</object>
	<object>
		<name>car</name>
		<pose>Unspecified</pose>
		<truncated>0</truncated>
		<difficult>0</difficult>
		<occluded>0</occluded>
		<bndbox>
			<xmin>117</xmin>
			<xmax>159</xmax>
			<ymin>249</ymin>
			<ymax>296</ymax>
		</bndbox>
	</object>
	<object>
		<name>car</name>
		<pose>Unspecified</pose>
		<truncated>0</truncated>
		<difficult>0</difficult>
		<occluded>0</occluded>
		<bndbox>
			<xmin>157</xmin>
			<xmax>174</xmax>
			<ymin>258</ymin>
			<ymax>286</ymax>
		</bndbox>
	</object>
	<object>
		<name>car</name>
		<pose>Unspecified</pose>
		<truncated>0</truncated>
		<difficult>0</difficult>
		<occluded>0</occluded>
		<bndbox>
			<xmin>173</xmin>
			<xmax>192</xmax>
			<ymin>253</ymin>
			<ymax>286</ymax>
		</bndbox>
	</object>
	<object>
		<name>car</name>
		<pose>Unspecified</pose>
		<truncated>0</truncated>
		<difficult>0</difficult>
		<occluded>0</occluded>
		<bndbox>
			<xmin>206</xmin>
			<xmax>255</xmax>
			<ymin>241</ymin>
			<ymax>314</ymax>
		</bndbox>
	</object>
	<object>
		<name>trafficLight-Green</name>
		<pose>Unspecified</pose>
		<truncated>0</truncated>
		<difficult>0</difficult>
		<occluded>0</occluded>
		<bndbox>
			<xmin>248</xmin>
			<xmax>256</xmax>
			<ymin>205</ymin>
			<ymax>226</ymax>
		</bndbox>
	</object>
	<object>
		<name>car</name>
		<pose>Unspecified</pose>
		<truncated>0</truncated>
		<difficult>0</difficult>
		<occluded>0</occluded>
		<bndbox>
			<xmin>378</xmin>
			<xmax>400</xmax>
			<ymin>243</ymin>
			<ymax>263</ymax>
		</bndbox>
	</object>
	<object>
		<name>biker</name>
		<pose>Unspecified</pose>
		<truncated>0</truncated>
		<difficult>0</difficult>
		<occluded>0</occluded>
		<bndbox>
			<xmin>436</xmin>
			<xmax>463</xmax>
			<ymin>208</ymin>
			<ymax>300</ymax>
		</bndbox>
	</object>
</annotation>
