<annotation>
	<folder></folder>
	<filename>1478898625095927773_jpg.rf.e913e0a77adf603de9c8d14d2590ba91.jpg</filename>
	<path>1478898625095927773_jpg.rf.e913e0a77adf603de9c8d14d2590ba91.jpg</path>
	<source>
		<database>roboflow.ai</database>
	</source>
	<size>
		<width>512</width>
		<height>512</height>
		<depth>3</depth>
	</size>
	<segmented>0</segmented>
	<object>
		<name>car</name>
		<pose>Unspecified</pose>
		<truncated>0</truncated>
		<difficult>0</difficult>
		<occluded>0</occluded>
		<bndbox>
			<xmin>2</xmin>
			<xmax>167</xmax>
			<ymin>239</ymin>
			<ymax>389</ymax>
		</bndbox>
	</object>
	<object>
		<name>truck</name>
		<pose>Unspecified</pose>
		<truncated>0</truncated>
		<difficult>0</difficult>
		<occluded>0</occluded>
		<bndbox>
			<xmin>178</xmin>
			<xmax>243</xmax>
			<ymin>218</ymin>
			<ymax>326</ymax>
		</bndbox>
	</object>
	<object>
		<name>pedestrian</name>
		<pose>Unspecified</pose>
		<truncated>0</truncated>
		<difficult>0</difficult>
		<occluded>0</occluded>
		<bndbox>
			<xmin>267</xmin>
			<xmax>286</xmax>
			<ymin>267</ymin>
			<ymax>340</ymax>
		</bndbox>
	</object>
	<object>
		<name>pedestrian</name>
		<pose>Unspecified</pose>
		<truncated>0</truncated>
		<difficult>0</difficult>
		<occluded>0</occluded>
		<bndbox>
			<xmin>279</xmin>
			<xmax>292</xmax>
			<ymin>271</ymin>
			<ymax>336</ymax>
		</bndbox>
	</object>
	<object>
		<name>pedestrian</name>
		<pose>Unspecified</pose>
		<truncated>0</truncated>
		<difficult>0</difficult>
		<occluded>0</occluded>
		<bndbox>
			<xmin>332</xmin>
			<xmax>355</xmax>
			<ymin>266</ymin>
			<ymax>336</ymax>
		</bndbox>
	</object>
	<object>
		<name>pedestrian</name>
		<pose>Unspecified</pose>
		<truncated>0</truncated>
		<difficult>0</difficult>
		<occluded>0</occluded>
		<bndbox>
			<xmin>385</xmin>
			<xmax>395</xmax>
			<ymin>278</ymin>
			<ymax>310</ymax>
		</bndbox>
	</object>
</annotation>
