<annotation>
	<folder></folder>
	<filename>1478900180717310993_jpg.rf.be9544efbb2d9d4011cae4ffa735ab2c.jpg</filename>
	<path>1478900180717310993_jpg.rf.be9544efbb2d9d4011cae4ffa735ab2c.jpg</path>
	<source>
		<database>roboflow.ai</database>
	</source>
	<size>
		<width>512</width>
		<height>512</height>
		<depth>3</depth>
	</size>
	<segmented>0</segmented>
	<object>
		<name>car</name>
		<pose>Unspecified</pose>
		<truncated>0</truncated>
		<difficult>0</difficult>
		<occluded>0</occluded>
		<bndbox>
			<xmin>375</xmin>
			<xmax>512</xmax>
			<ymin>250</ymin>
			<ymax>374</ymax>
		</bndbox>
	</object>
	<object>
		<name>car</name>
		<pose>Unspecified</pose>
		<truncated>0</truncated>
		<difficult>0</difficult>
		<occluded>0</occluded>
		<bndbox>
			<xmin>10</xmin>
			<xmax>63</xmax>
			<ymin>264</ymin>
			<ymax>309</ymax>
		</bndbox>
	</object>
	<object>
		<name>car</name>
		<pose>Unspecified</pose>
		<truncated>0</truncated>
		<difficult>0</difficult>
		<occluded>0</occluded>
		<bndbox>
			<xmin>155</xmin>
			<xmax>177</xmax>
			<ymin>262</ymin>
			<ymax>285</ymax>
		</bndbox>
	</object>
	<object>
		<name>car</name>
		<pose>Unspecified</pose>
		<truncated>0</truncated>
		<difficult>0</difficult>
		<occluded>0</occluded>
		<bndbox>
			<xmin>182</xmin>
			<xmax>194</xmax>
			<ymin>262</ymin>
			<ymax>279</ymax>
		</bndbox>
	</object>
	<object>
		<name>car</name>
		<pose>Unspecified</pose>
		<truncated>0</truncated>
		<difficult>0</difficult>
		<occluded>0</occluded>
		<bndbox>
			<xmin>201</xmin>
			<xmax>234</xmax>
			<ymin>256</ymin>
			<ymax>297</ymax>
		</bndbox>
	</object>
	<object>
		<name>car</name>
		<pose>Unspecified</pose>
		<truncated>0</truncated>
		<difficult>0</difficult>
		<occluded>0</occluded>
		<bndbox>
			<xmin>267</xmin>
			<xmax>287</xmax>
			<ymin>254</ymin>
			<ymax>291</ymax>
		</bndbox>
	</object>
	<object>
		<name>car</name>
		<pose>Unspecified</pose>
		<truncated>0</truncated>
		<difficult>0</difficult>
		<occluded>0</occluded>
		<bndbox>
			<xmin>280</xmin>
			<xmax>318</xmax>
			<ymin>250</ymin>
			<ymax>295</ymax>
		</bndbox>
	</object>
	<object>
		<name>car</name>
		<pose>Unspecified</pose>
		<truncated>0</truncated>
		<difficult>0</difficult>
		<occluded>0</occluded>
		<bndbox>
			<xmin>332</xmin>
			<xmax>418</xmax>
			<ymin>235</ymin>
			<ymax>339</ymax>
		</bndbox>
	</object>
</annotation>
