<annotation>
	<folder></folder>
	<filename>1478897147169768932_jpg.rf.86d723be6cb1425f839b88d3f3b797fa.jpg</filename>
	<path>1478897147169768932_jpg.rf.86d723be6cb1425f839b88d3f3b797fa.jpg</path>
	<source>
		<database>roboflow.ai</database>
	</source>
	<size>
		<width>512</width>
		<height>512</height>
		<depth>3</depth>
	</size>
	<segmented>0</segmented>
	<object>
		<name>car</name>
		<pose>Unspecified</pose>
		<truncated>0</truncated>
		<difficult>0</difficult>
		<occluded>0</occluded>
		<bndbox>
			<xmin>251</xmin>
			<xmax>279</xmax>
			<ymin>271</ymin>
			<ymax>306</ymax>
		</bndbox>
	</object>
	<object>
		<name>pedestrian</name>
		<pose>Unspecified</pose>
		<truncated>0</truncated>
		<difficult>0</difficult>
		<occluded>0</occluded>
		<bndbox>
			<xmin>20</xmin>
			<xmax>35</xmax>
			<ymin>269</ymin>
			<ymax>309</ymax>
		</bndbox>
	</object>
	<object>
		<name>car</name>
		<pose>Unspecified</pose>
		<truncated>0</truncated>
		<difficult>0</difficult>
		<occluded>0</occluded>
		<bndbox>
			<xmin>53</xmin>
			<xmax>90</xmax>
			<ymin>257</ymin>
			<ymax>301</ymax>
		</bndbox>
	</object>
	<object>
		<name>car</name>
		<pose>Unspecified</pose>
		<truncated>0</truncated>
		<difficult>0</difficult>
		<occluded>0</occluded>
		<bndbox>
			<xmin>55</xmin>
			<xmax>512</xmax>
			<ymin>195</ymin>
			<ymax>368</ymax>
		</bndbox>
	</object>
	<object>
		<name>trafficLight-Red</name>
		<pose>Unspecified</pose>
		<truncated>0</truncated>
		<difficult>0</difficult>
		<occluded>0</occluded>
		<bndbox>
			<xmin>64</xmin>
			<xmax>78</xmax>
			<ymin>202</ymin>
			<ymax>238</ymax>
		</bndbox>
	</object>
	<object>
		<name>trafficLight</name>
		<pose>Unspecified</pose>
		<truncated>0</truncated>
		<difficult>0</difficult>
		<occluded>0</occluded>
		<bndbox>
			<xmin>297</xmin>
			<xmax>312</xmax>
			<ymin>179</ymin>
			<ymax>219</ymax>
		</bndbox>
	</object>
</annotation>
