<annotation>
	<folder></folder>
	<filename>1478898746209121806_jpg.rf.495e61e6b230765c884fccf557a49852.jpg</filename>
	<path>1478898746209121806_jpg.rf.495e61e6b230765c884fccf557a49852.jpg</path>
	<source>
		<database>roboflow.ai</database>
	</source>
	<size>
		<width>512</width>
		<height>512</height>
		<depth>3</depth>
	</size>
	<segmented>0</segmented>
	<object>
		<name>truck</name>
		<pose>Unspecified</pose>
		<truncated>0</truncated>
		<difficult>0</difficult>
		<occluded>0</occluded>
		<bndbox>
			<xmin>368</xmin>
			<xmax>513</xmax>
			<ymin>1</ymin>
			<ymax>414</ymax>
		</bndbox>
	</object>
</annotation>
