<annotation>
	<folder></folder>
	<filename>1478895351606528500_jpg.rf.71akOhvgWo4f7nBMXSsk.jpg</filename>
	<path>1478895351606528500_jpg.rf.71akOhvgWo4f7nBMXSsk.jpg</path>
	<source>
		<database>roboflow.ai</database>
	</source>
	<size>
		<width>512</width>
		<height>512</height>
		<depth>3</depth>
	</size>
	<segmented>0</segmented>
	<object>
		<name>car</name>
		<pose>Unspecified</pose>
		<truncated>0</truncated>
		<difficult>0</difficult>
		<occluded>0</occluded>
		<bndbox>
			<xmin>211</xmin>
			<xmax>241</xmax>
			<ymin>260</ymin>
			<ymax>301</ymax>
		</bndbox>
	</object>
</annotation>
