<annotation>
	<folder></folder>
	<filename>1478895303046445445_jpg.rf.7c77ff2f6cf174e0353ef4fa4d81161d.jpg</filename>
	<path>1478895303046445445_jpg.rf.7c77ff2f6cf174e0353ef4fa4d81161d.jpg</path>
	<source>
		<database>roboflow.ai</database>
	</source>
	<size>
		<width>512</width>
		<height>512</height>
		<depth>3</depth>
	</size>
	<segmented>0</segmented>
	<object>
		<name>car</name>
		<pose>Unspecified</pose>
		<truncated>0</truncated>
		<difficult>0</difficult>
		<occluded>0</occluded>
		<bndbox>
			<xmin>73</xmin>
			<xmax>115</xmax>
			<ymin>290</ymin>
			<ymax>334</ymax>
		</bndbox>
	</object>
	<object>
		<name>car</name>
		<pose>Unspecified</pose>
		<truncated>0</truncated>
		<difficult>0</difficult>
		<occluded>0</occluded>
		<bndbox>
			<xmin>80</xmin>
			<xmax>110</xmax>
			<ymin>295</ymin>
			<ymax>328</ymax>
		</bndbox>
	</object>
</annotation>
