<annotation>
	<folder></folder>
	<filename>1478900038467235359_jpg.rf.4pvOp77J2MTlnw0kJ2bb.jpg</filename>
	<path>1478900038467235359_jpg.rf.4pvOp77J2MTlnw0kJ2bb.jpg</path>
	<source>
		<database>roboflow.ai</database>
	</source>
	<size>
		<width>512</width>
		<height>512</height>
		<depth>3</depth>
	</size>
	<segmented>0</segmented>
	<object>
		<name>car</name>
		<pose>Unspecified</pose>
		<truncated>0</truncated>
		<difficult>0</difficult>
		<occluded>0</occluded>
		<bndbox>
			<xmin>129</xmin>
			<xmax>172</xmax>
			<ymin>265</ymin>
			<ymax>285</ymax>
		</bndbox>
	</object>
	<object>
		<name>car</name>
		<pose>Unspecified</pose>
		<truncated>0</truncated>
		<difficult>0</difficult>
		<occluded>0</occluded>
		<bndbox>
			<xmin>344</xmin>
			<xmax>378</xmax>
			<ymin>254</ymin>
			<ymax>272</ymax>
		</bndbox>
	</object>
</annotation>
