<annotation>
	<folder></folder>
	<filename>1478900536631783113_jpg.rf.vgVumZOnjYsSIpUHWNIA.jpg</filename>
	<path>1478900536631783113_jpg.rf.vgVumZOnjYsSIpUHWNIA.jpg</path>
	<source>
		<database>roboflow.ai</database>
	</source>
	<size>
		<width>512</width>
		<height>512</height>
		<depth>3</depth>
	</size>
	<segmented>0</segmented>
	<object>
		<name>trafficLight-Green</name>
		<pose>Unspecified</pose>
		<truncated>0</truncated>
		<difficult>0</difficult>
		<occluded>0</occluded>
		<bndbox>
			<xmin>12</xmin>
			<xmax>21</xmax>
			<ymin>209</ymin>
			<ymax>237</ymax>
		</bndbox>
	</object>
	<object>
		<name>car</name>
		<pose>Unspecified</pose>
		<truncated>0</truncated>
		<difficult>0</difficult>
		<occluded>0</occluded>
		<bndbox>
			<xmin>78</xmin>
			<xmax>126</xmax>
			<ymin>240</ymin>
			<ymax>297</ymax>
		</bndbox>
	</object>
	<object>
		<name>car</name>
		<pose>Unspecified</pose>
		<truncated>0</truncated>
		<difficult>0</difficult>
		<occluded>0</occluded>
		<bndbox>
			<xmin>154</xmin>
			<xmax>221</xmax>
			<ymin>210</ymin>
			<ymax>309</ymax>
		</bndbox>
	</object>
	<object>
		<name>trafficLight-Green</name>
		<pose>Unspecified</pose>
		<truncated>0</truncated>
		<difficult>0</difficult>
		<occluded>0</occluded>
		<bndbox>
			<xmin>218</xmin>
			<xmax>228</xmax>
			<ymin>198</ymin>
			<ymax>225</ymax>
		</bndbox>
	</object>
	<object>
		<name>car</name>
		<pose>Unspecified</pose>
		<truncated>0</truncated>
		<difficult>0</difficult>
		<occluded>0</occluded>
		<bndbox>
			<xmin>276</xmin>
			<xmax>320</xmax>
			<ymin>223</ymin>
			<ymax>254</ymax>
		</bndbox>
	</object>
	<object>
		<name>car</name>
		<pose>Unspecified</pose>
		<truncated>0</truncated>
		<difficult>0</difficult>
		<occluded>0</occluded>
		<bndbox>
			<xmin>343</xmin>
			<xmax>373</xmax>
			<ymin>226</ymin>
			<ymax>245</ymax>
		</bndbox>
	</object>
</annotation>
