<annotation>
	<folder></folder>
	<filename>1478900088168750672_jpg.rf.y3WOO6axRJ1S4M4YQcdT.jpg</filename>
	<path>1478900088168750672_jpg.rf.y3WOO6axRJ1S4M4YQcdT.jpg</path>
	<source>
		<database>roboflow.ai</database>
	</source>
	<size>
		<width>512</width>
		<height>512</height>
		<depth>3</depth>
	</size>
	<segmented>0</segmented>
	<object>
		<name>car</name>
		<pose>Unspecified</pose>
		<truncated>0</truncated>
		<difficult>0</difficult>
		<occluded>0</occluded>
		<bndbox>
			<xmin>374</xmin>
			<xmax>513</xmax>
			<ymin>244</ymin>
			<ymax>430</ymax>
		</bndbox>
	</object>
	<object>
		<name>car</name>
		<pose>Unspecified</pose>
		<truncated>0</truncated>
		<difficult>0</difficult>
		<occluded>0</occluded>
		<bndbox>
			<xmin>30</xmin>
			<xmax>67</xmax>
			<ymin>275</ymin>
			<ymax>307</ymax>
		</bndbox>
	</object>
	<object>
		<name>car</name>
		<pose>Unspecified</pose>
		<truncated>0</truncated>
		<difficult>0</difficult>
		<occluded>0</occluded>
		<bndbox>
			<xmin>74</xmin>
			<xmax>117</xmax>
			<ymin>267</ymin>
			<ymax>289</ymax>
		</bndbox>
	</object>
	<object>
		<name>car</name>
		<pose>Unspecified</pose>
		<truncated>0</truncated>
		<difficult>0</difficult>
		<occluded>0</occluded>
		<bndbox>
			<xmin>219</xmin>
			<xmax>240</xmax>
			<ymin>256</ymin>
			<ymax>283</ymax>
		</bndbox>
	</object>
	<object>
		<name>car</name>
		<pose>Unspecified</pose>
		<truncated>0</truncated>
		<difficult>0</difficult>
		<occluded>0</occluded>
		<bndbox>
			<xmin>258</xmin>
			<xmax>272</xmax>
			<ymin>260</ymin>
			<ymax>283</ymax>
		</bndbox>
	</object>
	<object>
		<name>car</name>
		<pose>Unspecified</pose>
		<truncated>0</truncated>
		<difficult>0</difficult>
		<occluded>0</occluded>
		<bndbox>
			<xmin>279</xmin>
			<xmax>298</xmax>
			<ymin>248</ymin>
			<ymax>311</ymax>
		</bndbox>
	</object>
	<object>
		<name>car</name>
		<pose>Unspecified</pose>
		<truncated>0</truncated>
		<difficult>0</difficult>
		<occluded>0</occluded>
		<bndbox>
			<xmin>289</xmin>
			<xmax>350</xmax>
			<ymin>254</ymin>
			<ymax>324</ymax>
		</bndbox>
	</object>
	<object>
		<name>car</name>
		<pose>Unspecified</pose>
		<truncated>0</truncated>
		<difficult>0</difficult>
		<occluded>0</occluded>
		<bndbox>
			<xmin>294</xmin>
			<xmax>349</xmax>
			<ymin>258</ymin>
			<ymax>323</ymax>
		</bndbox>
	</object>
</annotation>
